dot/__init__.py
dot/borrowed_lazy.py
dot/dot.py
dotobject-1.3.1.dist-info/AUTHORS
dotobject-1.3.1.dist-info/LICENSE
dotobject-1.3.1.dist-info/METADATA
dotobject-1.3.1.dist-info/WHEEL
dotobject-1.3.1.dist-info/top_level.txt
dotobject-1.3.1.dist-info/RECORD
