Metadata-Version: 2.1
Name: dotobject
Version: 1.3.1
Summary: Dot notation object
Home-page: https://github.com/seperman/dotobject
Download-URL: https://github.com/seperman/dotobject/tarball/master
Author: Seperman
Author-email: sep@zepworks.com
License: MIT
Classifier: Intended Audience :: Developers
Classifier: Operating System :: OS Independent
Classifier: Topic :: Software Development
Classifier: Programming Language :: Python :: 3.7
Classifier: Programming Language :: Python :: 3.8
Classifier: Programming Language :: Python :: 3.9
Classifier: Programming Language :: Python :: 3.10
Classifier: Programming Language :: Python :: 3.11
Classifier: Development Status :: 5 - Production/Stable
Classifier: License :: OSI Approved :: MIT License
License-File: LICENSE
License-File: AUTHORS
